teex/__init__.py
teex/__version__.py
teex/_baseClasses/__init__.py
teex/_baseClasses/_baseClassifier.py
teex/_baseClasses/_baseDatasets.py
teex/_datasets/__init__.py
teex/_datasets/info/CUB200.py
teex/_datasets/info/OxfordIIT_Pet.py
teex/_datasets/info/__init__.py
teex/_datasets/info/kahikatea.py
teex/_datasets/info/newsgroup.py
teex/_utils/__init__.py
teex/_utils/_arrays.py
teex/_utils/_data.py
teex/_utils/_errors.py
teex/_utils/_misc.py
teex/_utils/_paths.py
teex/decisionRule/__init__.py
teex/decisionRule/data.py
teex/decisionRule/eval.py
teex/featureImportance/__init__.py
teex/featureImportance/data.py
teex/featureImportance/eval.py
teex/saliencyMap/__init__.py
teex/saliencyMap/data.py
teex/saliencyMap/eval.py
teex/wordImportance/__init__.py
teex/wordImportance/data.py
teex/wordImportance/eval.py
tests/__init__.py
tests/test_decisionRule.py
tests/test_featureImportance.py
tests/test_private.py
tests/test_saliencyMap.py
tests/test_wordImportance.py
teex-1.1.3.dist-info/LICENSE
teex-1.1.3.dist-info/METADATA
teex-1.1.3.dist-info/WHEEL
teex-1.1.3.dist-info/top_level.txt
teex-1.1.3.dist-info/RECORD
