Metadata-Version: 2.1
Name: teex
Version: 1.1.3
Summary: A Toolbox for the Evaluation of Explanations
Home-page: https://github.com/chus-chus/teex
Author: Jesus Antonanzas
Author-email: jesus.maria.antonanzas@estudiantat.upc.edu
Project-URL: Documentation, https://teex.readthedocs.io
Classifier: Programming Language :: Python :: 3 :: Only
Classifier: License :: OSI Approved :: MIT License
Classifier: Operating System :: OS Independent
Classifier: Development Status :: 4 - Beta
Requires-Python: <3.10,>=3.8
License-File: LICENSE
Requires-Dist: tqdm (>=4.61)
Requires-Dist: numpy (>=1.22)
Requires-Dist: scikit-learn (>=1.1)
Requires-Dist: scipy (>1.7)
Requires-Dist: sympy (>=1.8)
Requires-Dist: Pillow (>=9.0)
